gwas_sumstats_tools/cli.py
gwas_sumstats_tools/config.py
gwas_sumstats_tools/format.py
gwas_sumstats_tools/gen_meta.py
gwas_sumstats_tools/interfaces/data_table.py
gwas_sumstats_tools/interfaces/metadata.py
gwas_sumstats_tools/read.py
gwas_sumstats_tools/schema/configure_json.py
gwas_sumstats_tools/schema/data_table.py
gwas_sumstats_tools/schema/headermap.py
gwas_sumstats_tools/schema/metadata.py
gwas_sumstats_tools/schema/pre_defined_configure.py
gwas_sumstats_tools/utils.py
gwas_sumstats_tools/validate.py
gwas_sumstats_tools-1.0.24.dist-info/LICENSE
gwas_sumstats_tools-1.0.24.dist-info/METADATA
gwas_sumstats_tools-1.0.24.dist-info/WHEEL
gwas_sumstats_tools-1.0.24.dist-info/entry_points.txt
gwas_sumstats_tools-1.0.24.dist-info/RECORD
