Metadata-Version: 2.3
Name: gwas-sumstats-tools
Version: 1.0.24
Summary: 
Author: jdhayhurst
Author-email: jhayhurst@ebi.ac.uk
Requires-Python: >=3.9,<3.12
Classifier: Programming Language :: Python :: 3
Classifier: Programming Language :: Python :: 3.9
Classifier: Programming Language :: Python :: 3.10
Classifier: Programming Language :: Python :: 3.11
Requires-Dist: bsub (>=0.3.5,<0.4.0)
Requires-Dist: pandas (==1.5.3)
Requires-Dist: pandera (>=0.13.4,<0.14.0)
Requires-Dist: petl (>=1.7.12,<2.0.0)
Requires-Dist: pydantic (>=1.10.4,<2.0.0)
Requires-Dist: pyyaml (>=6.0,<7.0)
Requires-Dist: requests (>=2.28.2,<3.0.0)
Requires-Dist: ruamel-yaml (==0.17.32)
Requires-Dist: typer[all] (>=0.7.0,<0.8.0)
